algosikkr1/__init__.py
algosikkr1/core.py
algosikkr1-0.2.4.dist-info/licenses/LICENSE
algosikkr1-0.2.4.dist-info/METADATA
algosikkr1-0.2.4.dist-info/WHEEL
algosikkr1-0.2.4.dist-info/top_level.txt
algosikkr1-0.2.4.dist-info/RECORD
