Metadata-Version: 2.4
Name: algosikkr1
Version: 0.2.4
Summary: Моя первая библиотека на Python
Author-email: aboba228 <dddxxx722@gmail.com>
License-Expression: MIT
Requires-Python: >=3.8
License-File: LICENSE
Dynamic: license-file
